poetry_git_version_plugin/__init__.py
poetry_git_version_plugin/config.py
poetry_git_version_plugin/exceptions.py
poetry_git_version_plugin/plugins.py
poetry_git_version_plugin/services.py
poetry_git_version_plugin-2.0.1.dist-info/LICENSE
poetry_git_version_plugin-2.0.1.dist-info/METADATA
poetry_git_version_plugin-2.0.1.dist-info/WHEEL
poetry_git_version_plugin-2.0.1.dist-info/entry_points.txt
poetry_git_version_plugin-2.0.1.dist-info/top_level.txt
poetry_git_version_plugin-2.0.1.dist-info/RECORD
