Metadata-Version: 2.1
Name: poetry-git-version-plugin
Version: 2.0.1
Summary: Poetry plugin to get package version from git
Author-email: Alekse Marusich <alekse.marusich@rocshers.com>
License: MIT
Project-URL: Homepage, https://projects.rocshers.com/open-source/poetry-git-version-plugin
Project-URL: Repository, https://gitlab.com/rocshers/python/poetry-git-version-plugin
Keywords: rocshers,poetry,git
Classifier: License :: OSI Approved :: MIT License
Classifier: Intended Audience :: Developers
Classifier: Intended Audience :: Information Technology
Classifier: Intended Audience :: System Administrators
Classifier: Operating System :: OS Independent
Classifier: Topic :: Software Development :: Build Tools
Classifier: Topic :: Software Development :: Libraries :: Python Modules
Classifier: Topic :: Software Development :: Libraries
Classifier: Topic :: Software Development
Classifier: Topic :: System :: Archiving :: Packaging
Classifier: Topic :: System :: Installation/Setup
Classifier: Topic :: System :: Software Distribution
Classifier: Programming Language :: Python :: 3 :: Only
Classifier: Programming Language :: Python :: 3.12
Classifier: Programming Language :: Python :: 3.11
Classifier: Programming Language :: Python :: 3.10
Classifier: Programming Language :: Python :: 3
Classifier: Programming Language :: Python
Requires-Python: >=3.10
License-File: LICENSE
Requires-Dist: packaging-version-increment>=0.1.3
Requires-Dist: packaging-version-git>=0.1.2
Requires-Dist: pydantic>=2.7.0
Requires-Dist: pydantic-settings>=2.3.0
Requires-Dist: poetry>=1.3.2
